llama_index/llms/monsterapi/__init__.py
llama_index/llms/monsterapi/base.py
llama_index_llms_monsterapi-0.4.2.dist-info/METADATA
llama_index_llms_monsterapi-0.4.2.dist-info/WHEEL
llama_index_llms_monsterapi-0.4.2.dist-info/licenses/LICENSE
llama_index_llms_monsterapi-0.4.2.dist-info/RECORD
